paystackClient/__init__.py
paystackclient-0.1.0.dist-info/LICENSE
paystackclient-0.1.0.dist-info/METADATA
paystackclient-0.1.0.dist-info/WHEEL
paystackclient-0.1.0.dist-info/RECORD
