Metadata-Version: 2.1
Name: paystackClient
Version: 0.1.0
Summary: Paystack api implemented as a package, paystack-client is a simple project created by Joel .A.
License: MIT
Author: AnozieChibuike
Author-email: chibuikeanozie0@gmail.com
Requires-Python: >=3.5,<4.0
Classifier: License :: OSI Approved :: MIT License
Classifier: Programming Language :: Python :: 3
Classifier: Programming Language :: Python :: 3.5
Classifier: Programming Language :: Python :: 3.6
Classifier: Programming Language :: Python :: 3.7
Classifier: Programming Language :: Python :: 3.8
Classifier: Programming Language :: Python :: 3.9
Classifier: Programming Language :: Python :: 3.10
Classifier: Programming Language :: Python :: 3.11
